upg/__init__.py
upg/cli/__init__.py
upg/cli/commands.py
upg/config/__init__.py
upg/config/manager.py
upg/config/types.py
upg/core/__init__.py
upg/core/generator.py
upg/core/llm.py
upg/core/prompts/__init__.py
upg/core/prompts/floatingprompt.py
upg/core/prompts/metaprompt.py
upg_cli-1.0.0.dist-info/METADATA
upg_cli-1.0.0.dist-info/WHEEL
upg_cli-1.0.0.dist-info/entry_points.txt
upg_cli-1.0.0.dist-info/RECORD
