Metadata-Version: 2.1
Name: upg-cli
Version: 1.0.0
Summary: Ultimate Prompt Generator - A CLI tool for generating LLM prompts
Home-page: https://github.com/Afaneor/ultimate-prompt-generator
License: MIT
Keywords: llm,prompt,generator,cli,openai,anthropic
Author: npavlin
Author-email: afaneor@gmail.com
Requires-Python: >=3.11,<3.14
Classifier: Development Status :: 4 - Beta
Classifier: Environment :: Console
Classifier: Intended Audience :: Developers
Classifier: License :: OSI Approved :: MIT License
Classifier: Programming Language :: Python :: 3
Classifier: Programming Language :: Python :: 3.11
Classifier: Programming Language :: Python :: 3.12
Classifier: Topic :: Scientific/Engineering :: Artificial Intelligence
Classifier: Topic :: Software Development :: Libraries :: Python Modules
Requires-Dist: click (>=8.1.7,<9.0.0)
Requires-Dist: llama-index (>=0.12,<0.13)
Requires-Dist: llama-index-llms-anthropic (>=0.6.5,<0.7.0)
Requires-Dist: pydantic (>=2.0.0,<3.0.0)
Project-URL: Repository, https://github.com/Afaneor/ultimate-prompt-generator
